mysql_instance.py
py_ztj_mysql_instance-0.0.1.dist-info/METADATA
py_ztj_mysql_instance-0.0.1.dist-info/WHEEL
py_ztj_mysql_instance-0.0.1.dist-info/top_level.txt
py_ztj_mysql_instance-0.0.1.dist-info/RECORD
