Metadata-Version: 2.1
Name: py-ztj-mysql-instance
Version: 0.0.1
Summary: python mysql instance package
Home-page: http://github.com/ztj1993/PythonPackages/blob/master/py_mysql_instance
Author: ZhangTianJie
Author-email: ztj1993@gmail.com
License: MIT License
Keywords: mysql
Platform: UNKNOWN
Requires-Dist: pymysql
Requires-Dist: DBUtils
Requires-Dist: py-ztj-registry
